rsatoolbox/__init__.py
rsatoolbox/py.typed
rsatoolbox/resources.py
rsatoolbox/test.py
rsatoolbox/cengine/__init__.pxd
rsatoolbox/cengine/__init__.py
rsatoolbox/cengine/similarity.cp311-win_amd64.pyd
rsatoolbox/cengine/similarity.pyx
rsatoolbox/data/__init__.py
rsatoolbox/data/base.py
rsatoolbox/data/computations.py
rsatoolbox/data/dataset.py
rsatoolbox/data/noise.py
rsatoolbox/data/ops.py
rsatoolbox/inference/__init__.py
rsatoolbox/inference/boot_testset.py
rsatoolbox/inference/bootstrap.py
rsatoolbox/inference/crossvalsets.py
rsatoolbox/inference/evaluate.py
rsatoolbox/inference/noise_ceiling.py
rsatoolbox/inference/result.py
rsatoolbox/io/__init__.py
rsatoolbox/io/bids.py
rsatoolbox/io/fmriprep.py
rsatoolbox/io/hdf5.py
rsatoolbox/io/hrf.py
rsatoolbox/io/meadows.py
rsatoolbox/io/mne.py
rsatoolbox/io/optional.py
rsatoolbox/io/pandas.py
rsatoolbox/io/petnames.py
rsatoolbox/io/pkl.py
rsatoolbox/io/spm.py
rsatoolbox/model/__init__.py
rsatoolbox/model/fitter.py
rsatoolbox/model/model.py
rsatoolbox/model/model_family.py
rsatoolbox/rdm/__init__.py
rsatoolbox/rdm/calc.py
rsatoolbox/rdm/calc_unbalanced.py
rsatoolbox/rdm/combine.py
rsatoolbox/rdm/compare.py
rsatoolbox/rdm/pairs.py
rsatoolbox/rdm/rdms.py
rsatoolbox/rdm/transform.py
rsatoolbox/simulation/__init__.py
rsatoolbox/simulation/sim.py
rsatoolbox/util/__init__.py
rsatoolbox/util/build_rdm.py
rsatoolbox/util/data_utils.py
rsatoolbox/util/descriptor_utils.py
rsatoolbox/util/file_io.py
rsatoolbox/util/inference_util.py
rsatoolbox/util/matrix.py
rsatoolbox/util/pooling.py
rsatoolbox/util/rdm_utils.py
rsatoolbox/util/searchlight.py
rsatoolbox/util/weighted_mds.py
rsatoolbox/vis/__init__.py
rsatoolbox/vis/colors.py
rsatoolbox/vis/icon.py
rsatoolbox/vis/model_map.py
rsatoolbox/vis/model_plot.py
rsatoolbox/vis/modelfamily_graph.py
rsatoolbox/vis/rdm.mplstyle
rsatoolbox/vis/rdm_comparison.py
rsatoolbox/vis/rdm_plot.py
rsatoolbox/vis/scatter_plot.py
rsatoolbox/vis/timecourse.py
rsatoolbox-0.3.2.dist-info/licenses/LICENSE
rsatoolbox-0.3.2.dist-info/METADATA
rsatoolbox-0.3.2.dist-info/WHEEL
rsatoolbox-0.3.2.dist-info/top_level.txt
rsatoolbox-0.3.2.dist-info/RECORD
