Metadata-Version: 2.4
Name: rsatoolbox
Version: 0.3.2
Summary: Representational Similarity Analysis (RSA) in Python
Author: rsatoolbox authors
License-Expression: MIT
Project-URL: homepage, https://github.com/rsagroup/rsatoolbox
Project-URL: documentation, https://rsatoolbox.readthedocs.io/
Keywords: neuroscience
Classifier: Programming Language :: Python
Classifier: Operating System :: OS Independent
Classifier: Development Status :: 4 - Beta
Classifier: Topic :: Scientific/Engineering
Classifier: Intended Audience :: Science/Research
Classifier: Programming Language :: Python :: 3.10
Classifier: Programming Language :: Python :: 3.11
Classifier: Programming Language :: Python :: 3.12
Classifier: Programming Language :: Python :: 3.13
Classifier: Programming Language :: Python :: 3.14
Requires-Python: >=3.10
License-File: LICENSE
Requires-Dist: numpy>=1.21.2
Requires-Dist: scipy>=1.10.1
Requires-Dist: scikit-learn
Requires-Dist: scikit-image
Requires-Dist: pandas
Requires-Dist: matplotlib
Requires-Dist: h5py
Requires-Dist: tqdm
Requires-Dist: joblib
Requires-Dist: networkx>=3.0
Provides-Extra: imaging
Requires-Dist: mne~=1.5.1; extra == "imaging"
Requires-Dist: nibabel~=5.1.0; extra == "imaging"
Requires-Dist: neuroimagingtools~=1.1.4; extra == "imaging"
Dynamic: license-file
